<?xml version="1.0" encoding="utf-8" ?>
<dwsync>
<file name="120px-WVO_Controller_Proto_1_Wires.JPG" server="wvodesigns.com" local="131557533825555670" remote="131251284000000000" Dst="1" />
<file name="1024px-WVO_Controller_Proto_1_Wires.JPG" server="wvodesigns.com" local="131557533828522871" remote="131251284000000000" Dst="1" />
<file name="1000px-WVO_Controller_Proto_1_Wires.JPG" server="wvodesigns.com" local="131557533829733126" remote="131251284000000000" Dst="1" />
<file name="125px-WVO_Controller_Proto_1_Wires.JPG" server="wvodesigns.com" local="131557533829783133" remote="131251284000000000" Dst="1" />
<file name="180px-WVO_Controller_Proto_1_Wires.JPG" server="wvodesigns.com" local="131557533835394158" remote="131251284000000000" Dst="1" />
<file name="300px-WVO_Controller_Proto_1_Wires.JPG" server="wvodesigns.com" local="131557533836096052" remote="131251284000000000" Dst="1" />
<file name="320px-WVO_Controller_Proto_1_Wires.JPG" server="wvodesigns.com" local="131557533839899166" remote="131251284000000000" Dst="1" />
<file name="1280px-WVO_Controller_Proto_1_Wires.JPG" server="wvodesigns.com" local="131557533840580183" remote="131251284000000000" Dst="1" />
<file name="500px-WVO_Controller_Proto_1_Wires.JPG" server="wvodesigns.com" local="131557533842476241" remote="131251284000000000" Dst="1" />
<file name="640px-WVO_Controller_Proto_1_Wires.JPG" server="wvodesigns.com" local="131557533844574560" remote="131251284000000000" Dst="1" />
<file name="750px-WVO_Controller_Proto_1_Wires.JPG" server="wvodesigns.com" local="131557533848858971" remote="131251284000000000" Dst="1" />
<file name="800px-WVO_Controller_Proto_1_Wires.JPG" server="wvodesigns.com" local="131557533851300980" remote="131251284000000000" Dst="1" />
</dwsync>