<?xml version="1.0" encoding="utf-8" ?>
<dwsync>
<file name="120px-Thurston02.JPG" server="wvodesigns.com" local="131557534975491091" remote="131251284000000000" Dst="1" />
<file name="1024px-Thurston02.JPG" server="wvodesigns.com" local="131557534976397089" remote="131251284000000000" Dst="1" />
<file name="1000px-Thurston02.JPG" server="wvodesigns.com" local="131557534978478825" remote="131252148000000000" Dst="1" />
<file name="180px-Thurston02.JPG" server="wvodesigns.com" local="131557534981838850" remote="131251284000000000" Dst="1" />
<file name="320px-Thurston02.JPG" server="wvodesigns.com" local="131557534982463548" remote="131251284000000000" Dst="1" />
<file name="1280px-Thurston02.JPG" server="wvodesigns.com" local="131557534983109111" remote="131251284000000000" Dst="1" />
<file name="500px-Thurston02.JPG" server="wvodesigns.com" local="131557534986142137" remote="131251284000000000" Dst="1" />
<file name="640px-Thurston02.JPG" server="wvodesigns.com" local="131557534989440872" remote="131251284000000000" Dst="1" />
<file name="750px-Thurston02.JPG" server="wvodesigns.com" local="131557534990697171" remote="131252148000000000" Dst="1" />
<file name="800px-Thurston02.JPG" server="wvodesigns.com" local="131557534992453283" remote="131251284000000000" Dst="1" />
</dwsync>