<?xml version="1.0" encoding="utf-8" ?>
<dwsync>
<file name="120px-7.3IDI_2.JPG" server="wvodesigns.com" local="131557536368197146" remote="131251284000000000" Dst="1" />
<file name="1024px-7.3IDI_2.JPG" server="wvodesigns.com" local="131557536369204718" remote="131251284000000000" Dst="1" />
<file name="1000px-7.3IDI_2.JPG" server="wvodesigns.com" local="131557536371212322" remote="131252148000000000" Dst="1" />
<file name="180px-7.3IDI_2.JPG" server="wvodesigns.com" local="131557536374294958" remote="131251284000000000" Dst="1" />
<file name="320px-7.3IDI_2.JPG" server="wvodesigns.com" local="131557536375551741" remote="131251284000000000" Dst="1" />
<file name="1280px-7.3IDI_2.JPG" server="wvodesigns.com" local="131557536377403009" remote="131251284000000000" Dst="1" />
<file name="500px-7.3IDI_2.JPG" server="wvodesigns.com" local="131557536380713377" remote="131251284000000000" Dst="1" />
<file name="640px-7.3IDI_2.JPG" server="wvodesigns.com" local="131557536381329454" remote="131251284000000000" Dst="1" />
<file name="750px-7.3IDI_2.JPG" server="wvodesigns.com" local="131557536384526793" remote="131252148000000000" Dst="1" />
<file name="800px-7.3IDI_2.JPG" server="wvodesigns.com" local="131557536385227327" remote="131251284000000000" Dst="1" />
</dwsync>